[
  {
    "members" : [
      [
        [
        ],
        {
          "DefModule" : {
            "node" : {
              "AstNode" : {
                "data" : {
                  "name" : "main",
                  "members" : [
                    [
                      [
                      ],
                      {
                        "DefComponentInstance" : {
                          "node" : {
                            "AstNode" : {
                              "data" : {
                                "name" : "main_a",
                                "component" : {
                                  "AstNode" : {
                                    "data" : {
                                      "Qualified" : {
                                        "qualifier" : {
                                          "AstNode" : {
                                            "data" : {
                                              "Unqualified" : {
                                                "name" : "Components"
                                              }
                                            },
                                            "id" : 132
                                          }
                                        },
                                        "name" : {
                                          "AstNode" : {
                                            "data" : "A",
                                            "id" : 133
                                          }
                                        }
                                      }
                                    },
                                    "id" : 134
                                  }
                                },
                                "baseId" : {
                                  "AstNode" : {
                                    "data" : {
                                      "ExprLiteralInt" : {
                                        "value" : "0xAB"
                                      }
                                    },
                                    "id" : 135
                                  }
                                },
                                "implType" : "None",
                                "file" : "None",
                                "queueSize" : "None",
                                "stackSize" : "None",
                                "priority" : "None",
                                "cpu" : "None",
                                "initSpecs" : [
                                ]
                              },
                              "id" : 136
                            }
                          }
                        }
                      },
                      [
                      ]
                    ],
                    [
                      [
                      ],
                      {
                        "DefComponentInstance" : {
                          "node" : {
                            "AstNode" : {
                              "data" : {
                                "name" : "b",
                                "component" : {
                                  "AstNode" : {
                                    "data" : {
                                      "Qualified" : {
                                        "qualifier" : {
                                          "AstNode" : {
                                            "data" : {
                                              "Unqualified" : {
                                                "name" : "Components"
                                              }
                                            },
                                            "id" : 137
                                          }
                                        },
                                        "name" : {
                                          "AstNode" : {
                                            "data" : "B",
                                            "id" : 138
                                          }
                                        }
                                      }
                                    },
                                    "id" : 139
                                  }
                                },
                                "baseId" : {
                                  "AstNode" : {
                                    "data" : {
                                      "ExprLiteralInt" : {
                                        "value" : "0xBC"
                                      }
                                    },
                                    "id" : 140
                                  }
                                },
                                "implType" : "None",
                                "file" : "None",
                                "queueSize" : {
                                  "Some" : {
                                    "AstNode" : {
                                      "data" : {
                                        "ExprDot" : {
                                          "e" : {
                                            "AstNode" : {
                                              "data" : {
                                                "ExprIdent" : {
                                                  "value" : "Defaults"
                                                }
                                              },
                                              "id" : 141
                                            }
                                          },
                                          "id" : {
                                            "AstNode" : {
                                              "data" : "QUEUE_SIZE",
                                              "id" : 142
                                            }
                                          }
                                        }
                                      },
                                      "id" : 143
                                    }
                                  }
                                },
                                "stackSize" : {
                                  "Some" : {
                                    "AstNode" : {
                                      "data" : {
                                        "ExprDot" : {
                                          "e" : {
                                            "AstNode" : {
                                              "data" : {
                                                "ExprIdent" : {
                                                  "value" : "Defaults"
                                                }
                                              },
                                              "id" : 144
                                            }
                                          },
                                          "id" : {
                                            "AstNode" : {
                                              "data" : "STACK_SIZE",
                                              "id" : 145
                                            }
                                          }
                                        }
                                      },
                                      "id" : 146
                                    }
                                  }
                                },
                                "priority" : {
                                  "Some" : {
                                    "AstNode" : {
                                      "data" : {
                                        "ExprLiteralInt" : {
                                          "value" : "100"
                                        }
                                      },
                                      "id" : 147
                                    }
                                  }
                                },
                                "cpu" : "None",
                                "initSpecs" : [
                                ]
                              },
                              "id" : 148
                            }
                          }
                        }
                      },
                      [
                      ]
                    ],
                    [
                      [
                      ],
                      {
                        "DefComponentInstance" : {
                          "node" : {
                            "AstNode" : {
                              "data" : {
                                "name" : "main_c",
                                "component" : {
                                  "AstNode" : {
                                    "data" : {
                                      "Qualified" : {
                                        "qualifier" : {
                                          "AstNode" : {
                                            "data" : {
                                              "Unqualified" : {
                                                "name" : "Components"
                                              }
                                            },
                                            "id" : 149
                                          }
                                        },
                                        "name" : {
                                          "AstNode" : {
                                            "data" : "C",
                                            "id" : 150
                                          }
                                        }
                                      }
                                    },
                                    "id" : 151
                                  }
                                },
                                "baseId" : {
                                  "AstNode" : {
                                    "data" : {
                                      "ExprLiteralInt" : {
                                        "value" : "0xCD"
                                      }
                                    },
                                    "id" : 152
                                  }
                                },
                                "implType" : "None",
                                "file" : "None",
                                "queueSize" : {
                                  "Some" : {
                                    "AstNode" : {
                                      "data" : {
                                        "ExprDot" : {
                                          "e" : {
                                            "AstNode" : {
                                              "data" : {
                                                "ExprIdent" : {
                                                  "value" : "Defaults"
                                                }
                                              },
                                              "id" : 153
                                            }
                                          },
                                          "id" : {
                                            "AstNode" : {
                                              "data" : "QUEUE_SIZE",
                                              "id" : 154
                                            }
                                          }
                                        }
                                      },
                                      "id" : 155
                                    }
                                  }
                                },
                                "stackSize" : "None",
                                "priority" : "None",
                                "cpu" : "None",
                                "initSpecs" : [
                                ]
                              },
                              "id" : 156
                            }
                          }
                        }
                      },
                      [
                      ]
                    ],
                    [
                      [
                      ],
                      {
                        "DefTopology" : {
                          "node" : {
                            "AstNode" : {
                              "data" : {
                                "name" : "MyST",
                                "members" : [
                                ]
                              },
                              "id" : 157
                            }
                          }
                        }
                      },
                      [
                        "! is st.st base id 0xCCCC with {",
                        "!    st.a = main.main_a",
                        "! }"
                      ]
                    ],
                    [
                      [
                      ],
                      {
                        "DefTopology" : {
                          "node" : {
                            "AstNode" : {
                              "data" : {
                                "name" : "main",
                                "members" : [
                                  [
                                    [
                                    ],
                                    {
                                      "SpecTopImport" : {
                                        "node" : {
                                          "AstNode" : {
                                            "data" : {
                                              "top" : {
                                                "AstNode" : {
                                                  "data" : {
                                                    "Qualified" : {
                                                      "qualifier" : {
                                                        "AstNode" : {
                                                          "data" : {
                                                            "Unqualified" : {
                                                              "name" : "st"
                                                            }
                                                          },
                                                          "id" : 192
                                                        }
                                                      },
                                                      "name" : {
                                                        "AstNode" : {
                                                          "data" : "MyST",
                                                          "id" : 193
                                                        }
                                                      }
                                                    }
                                                  },
                                                  "id" : 194
                                                }
                                              }
                                            },
                                            "id" : 195
                                          }
                                        }
                                      }
                                    },
                                    [
                                    ]
                                  ]
                                ]
                              },
                              "id" : 196
                            }
                          }
                        }
                      },
                      [
                      ]
                    ]
                  ]
                },
                "id" : 197
              }
            }
          }
        },
        [
        ]
      ]
    ]
  }
]
